.VERSION
AUTHORS.rst
CONTRIBUTING.rst
HISTORY.rst
LICENSE
MANIFEST.in
Pipfile
Pipfile.lock
README.rst
USAGE.rst
cli.py
dev-requirements.txt
requirements.txt
setup.cfg
setup.py
awsapicli/.VERSION
awsapicli/AUTHORS.rst
awsapicli/CONTRIBUTING.rst
awsapicli/HISTORY.rst
awsapicli/LICENSE
awsapicli/Pipfile
awsapicli/Pipfile.lock
awsapicli/README.rst
awsapicli/USAGE.rst
awsapicli/__init__.py
awsapicli/_version.py
awsapicli/actions.py
awsapicli/awsapicli.py
awsapicli/awsapicliexceptions.py
awsapicli/dev-requirements.txt
awsapicli/options.py
awsapicli/requirements.txt
awsapicli/validators.py
awsapicli.egg-info/PKG-INFO
awsapicli.egg-info/SOURCES.txt
awsapicli.egg-info/dependency_links.txt
awsapicli.egg-info/entry_points.txt
awsapicli.egg-info/not-zip-safe
awsapicli.egg-info/requires.txt
awsapicli.egg-info/top_level.txt
awsapicli/conf/logging.json-example
docs/Makefile
docs/authors.rst
docs/conf.py
docs/contributing.rst
docs/history.rst
docs/index.rst
docs/installation.rst
docs/readme.rst
docs/usage.rst