Metadata-Version: 2.1
Name: awsapicli
Version: 0.1.6
Summary: A cli tool exposing capabilities of awsapilib like control tower account creation, account renaming and email updating, account termination and more.
Home-page: https://github.com/schubergphilis/awsapicli.git
Author: Costas Tyfoxylos
Author-email: ctyfoxylos@schubergphilis.com
License: MIT
Keywords: awsapicli aws api
Platform: UNKNOWN
Classifier: Development Status :: 4 - Beta
Classifier: Intended Audience :: Developers
Classifier: License :: OSI Approved :: MIT License
Classifier: Natural Language :: English
Classifier: Programming Language :: Python :: 3.7
License-File: LICENSE
License-File: AUTHORS.rst
